setup.py
piped.contrib.database.egg-info/PKG-INFO
piped.contrib.database.egg-info/SOURCES.txt
piped.contrib.database.egg-info/dependency_links.txt
piped.contrib.database.egg-info/requires.txt
piped.contrib.database.egg-info/top_level.txt
piped/plugins/database_providers.py
piped_database/__init__.py
piped_database/db.py
piped_database/providers.py
piped_database/service.py
piped_database/test/__init__.py
piped_database/test/test_database.py