Metadata-Version: 1.1
Name: piped.contrib.database
Version: 0.7.0
Summary: Database provider for Piped.
Home-page: http://piped.io
Author: Piped Project Contributors
Author-email: piped@librelist.com
License: MIT
Platform: UNKNOWN
Classifier: Development Status :: 3 - Alpha
Classifier: Environment :: Plugins
Classifier: Framework :: Twisted
Classifier: Operating System :: OS Independent
Classifier: Topic :: Database
